lowball/__init__.py
lowball/core.py
lowball/exceptions.py
lowball/authentication/__init__.py
lowball/authentication/authentication.py
lowball/authentication/wrappers.py
lowball/builtins/__init__.py
lowball/builtins/error_handler/__init__.py
lowball/builtins/error_handler/error_handler.py
lowball/builtins/logging/__init__.py
lowball/builtins/logging/formatter.py
lowball/builtins/logging/logging_handler.py
lowball/builtins/providers/__init__.py
lowball/builtins/providers/auth_db.py
lowball/builtins/providers/auth_provider.py
lowball/builtins/response_class/__init__.py
lowball/builtins/response_class/response_class.py
lowball/builtins/signal_subscribers/__init__.py
lowball/builtins/signal_subscribers/request_finished_log.py
lowball/models/__init__.py
lowball/models/authentication_models/__init__.py
lowball/models/authentication_models/clientdata.py
lowball/models/authentication_models/token.py
lowball/models/config_models/__init__.py
lowball/models/config_models/config.py
lowball/models/provider_models/__init__.py
lowball/models/provider_models/auth_db.py
lowball/models/provider_models/auth_provider.py
lowball/routes/__init__.py
lowball/routes/builtins/__init__.py
lowball/routes/builtins/auth.py
lowball/routes/builtins/status.py
tests/__init__.py
tests/lowball/__init__.py
tests/lowball/conftest.py
tests/lowball/test_core.py
tests/lowball/authentication/__init__.py
tests/lowball/authentication/conftest.py
tests/lowball/authentication/test_authentication.py
tests/lowball/authentication/test_wrappers.py
tests/lowball/builtins/__init__.py
tests/lowball/builtins/conftest.py
tests/lowball/builtins/error_handler/__init__.py
tests/lowball/builtins/error_handler/conftest.py
tests/lowball/builtins/error_handler/test_error_handler.py
tests/lowball/builtins/logging/__init__.py
tests/lowball/builtins/logging/conftest.py
tests/lowball/builtins/logging/test_formatter.py
tests/lowball/builtins/logging/test_logging_handler.py
tests/lowball/builtins/providers/__init__.py
lowball-1.0.4.dist-info/LICENSE
lowball-1.0.4.dist-info/METADATA
lowball-1.0.4.dist-info/WHEEL
lowball-1.0.4.dist-info/top_level.txt
lowball-1.0.4.dist-info/RECORD
